testjump.py
testjump-0.1.6.dist-info/licenses/LICENSE
testjump-0.1.6.dist-info/METADATA
testjump-0.1.6.dist-info/WHEEL
testjump-0.1.6.dist-info/entry_points.txt
testjump-0.1.6.dist-info/top_level.txt
testjump-0.1.6.dist-info/RECORD
