Metadata-Version: 2.4
Name: testjump
Version: 0.1.6
Summary: A CLI tool that helps you quickly navigate to test functions in pytest files.
Project-URL: Homepage, https://github.com/greatbahram/testjump
Project-URL: Changelog, https://github.com/greatbahram/testjump/releases
Project-URL: Issues, https://github.com/greatbahram/testjump/issues
Project-URL: CI, https://github.com/greatbahram/testjump/actions
Requires-Python: >=3.12
License-File: LICENSE
Provides-Extra: dev
Requires-Dist: pre-commit>=4.2.0; extra == "dev"
Requires-Dist: pytest>=8.3.5; extra == "dev"
Requires-Dist: ruff>=0.11.2; extra == "dev"
Dynamic: license-file
